{"nodes": [{"id": "src_components_table_tableview_jsx", "label": "TableView.jsx", "file_type": "code", "source_file": "src/components/table/TableView.jsx", "source_location": "L1"}, {"id": "tableview_tableskeleton", "label": "TableSkeleton()", "file_type": "code", "source_file": "src/components/table/TableView.jsx", "source_location": "L22"}, {"id": "tableview_statusbadge", "label": "StatusBadge()", "file_type": "code", "source_file": "src/components/table/TableView.jsx", "source_location": "L78"}, {"id": "tableview_prioritybadge", "label": "PriorityBadge()", "file_type": "code", "source_file": "src/components/table/TableView.jsx", "source_location": "L92"}, {"id": "tableview_assigneeavatar", "label": "AssigneeAvatar()", "file_type": "code", "source_file": "src/components/table/TableView.jsx", "source_location": "L108"}, {"id": "tableview_assigneeavatars", "label": "AssigneeAvatars()", "file_type": "code", "source_file": "src/components/table/TableView.jsx", "source_location": "L148"}, {"id": "tableview_sorticon", "label": "SortIcon()", "file_type": "code", "source_file": "src/components/table/TableView.jsx", "source_location": "L262"}, {"id": "tableview_tableview", "label": "TableView()", "file_type": "code", "source_file": "src/components/table/TableView.jsx", "source_location": "L272"}], "edges": [{"source": "src_components_table_tableview_jsx", "target": "react", "relation": "imports_from", "confidence": "EXTRACTED", "source_file": "src/components/table/TableView.jsx", "source_location": "L1", "weight": 1.0}, {"source": "src_components_table_tableview_jsx", "target": "react_table", "relation": "imports_from", "confidence": "EXTRACTED", "source_file": "src/components/table/TableView.jsx", "source_location": "L2", "weight": 1.0}, {"source": "src_components_table_tableview_jsx", "target": "dayjs", "relation": "imports_from", "confidence": "EXTRACTED", "source_file": "src/components/table/TableView.jsx", "source_location": "L10", "weight": 1.0}, {"source": "src_components_table_tableview_jsx", "target": "framer_motion", "relation": "imports_from", "confidence": "EXTRACTED", "source_file": "src/components/table/TableView.jsx", "source_location": "L11", "weight": 1.0}, {"source": "src_components_table_tableview_jsx", "target": "react", "relation": "imports_from", "confidence": "EXTRACTED", "source_file": "src/components/table/TableView.jsx", "source_location": "L12", "weight": 1.0}, {"source": "src_components_table_tableview_jsx", "target": "fi", "relation": "imports_from", "confidence": "EXTRACTED", "source_file": "src/components/table/TableView.jsx", "source_location": "L13", "weight": 1.0}, {"source": "src_components_table_tableview_jsx", "target": "src_components_table_service_apiservice_ts", "relation": "imports_from", "confidence": "EXTRACTED", "source_file": "src/components/table/TableView.jsx", "source_location": "L14", "weight": 1.0}, {"source": "src_components_table_tableview_jsx", "target": "src_components_table_contexts_filtercontext_tsx", "relation": "imports_from", "confidence": "EXTRACTED", "source_file": "src/components/table/TableView.jsx", "source_location": "L15", "weight": 1.0}, {"source": "src_components_table_tableview_jsx", "target": "src_components_table_utils_imagehelpers_ts", "relation": "imports_from", "confidence": "EXTRACTED", "source_file": "src/components/table/TableView.jsx", "source_location": "L16", "weight": 1.0}, {"source": "src_components_table_tableview_jsx", "target": "src_components_table_skeleton_tsx", "relation": "imports_from", "confidence": "EXTRACTED", "source_file": "src/components/table/TableView.jsx", "source_location": "L17", "weight": 1.0}, {"source": "src_components_table_tableview_jsx", "target": "src_components_table_task_taskdetailpanel_tsx", "relation": "imports_from", "confidence": "EXTRACTED", "source_file": "src/components/table/TableView.jsx", "source_location": "L18", "weight": 1.0}, {"source": "src_components_table_tableview_jsx", "target": "tableview_tableskeleton", "relation": "contains", "confidence": "EXTRACTED", "source_file": "src/components/table/TableView.jsx", "source_location": "L22", "weight": 1.0}, {"source": "src_components_table_tableview_jsx", "target": "tableview_statusbadge", "relation": "contains", "confidence": "EXTRACTED", "source_file": "src/components/table/TableView.jsx", "source_location": "L78", "weight": 1.0}, {"source": "src_components_table_tableview_jsx", "target": "tableview_prioritybadge", "relation": "contains", "confidence": "EXTRACTED", "source_file": "src/components/table/TableView.jsx", "source_location": "L92", "weight": 1.0}, {"source": "src_components_table_tableview_jsx", "target": "tableview_assigneeavatar", "relation": "contains", "confidence": "EXTRACTED", "source_file": "src/components/table/TableView.jsx", "source_location": "L108", "weight": 1.0}, {"source": "src_components_table_tableview_jsx", "target": "tableview_assigneeavatars", "relation": "contains", "confidence": "EXTRACTED", "source_file": "src/components/table/TableView.jsx", "source_location": "L148", "weight": 1.0}, {"source": "src_components_table_tableview_jsx", "target": "tableview_sorticon", "relation": "contains", "confidence": "EXTRACTED", "source_file": "src/components/table/TableView.jsx", "source_location": "L262", "weight": 1.0}, {"source": "src_components_table_tableview_jsx", "target": "tableview_tableview", "relation": "contains", "confidence": "EXTRACTED", "source_file": "src/components/table/TableView.jsx", "source_location": "L272", "weight": 1.0}]}